switchObject/__init__.py
switchObject-1.2.0.1.dist-info/LICENSE
switchObject-1.2.0.1.dist-info/METADATA
switchObject-1.2.0.1.dist-info/WHEEL
switchObject-1.2.0.1.dist-info/top_level.txt
switchObject-1.2.0.1.dist-info/RECORD
